qcis_sim/__init__.py
qcis_sim/config_66bit.json
qcis_sim/gate.py
qcis_sim/run.py
qcis_sim/topo.py
qcis_sim/backend/__init__.py
qcis_sim/backend/numpy_backend.py
qcis_sim/backend/state_vector_simulator.py
qcis_sim/backend/torch_backend.py
qcis_sim-0.1.0.dist-info/LICENSE
qcis_sim-0.1.0.dist-info/METADATA
qcis_sim-0.1.0.dist-info/WHEEL
qcis_sim-0.1.0.dist-info/top_level.txt
qcis_sim-0.1.0.dist-info/RECORD
