Metadata-Version: 2.1
Name: qcis-sim
Version: 0.1.0
Summary: simulation tools for QCIS
Author: Yusheng Yang
Author-email: yangys@arclightquantum.com
License: MIT
Platform: python 3.8+
Requires-Python: >=3.8
License-File: LICENSE
Requires-Dist: numpy
